reckomate_sdk/__init__.py
reckomate_sdk/client.py
reckomate_sdk/context.py
reckomate_sdk/exceptions.py
reckomate_sdk/py.typed
reckomate_sdk/schemas/__init__.py
reckomate_sdk/services/__init__.py
reckomate_sdk/services/admin.py
reckomate_sdk/services/chat.py
reckomate_sdk/services/ingest.py
reckomate_sdk/services/rag.py
reckomate_sdk/services/upload.py
reckomate_sdk/services/user.py
reckomate_ai_sdk-0.2.0.dist-info/METADATA
reckomate_ai_sdk-0.2.0.dist-info/WHEEL
reckomate_ai_sdk-0.2.0.dist-info/top_level.txt
reckomate_ai_sdk-0.2.0.dist-info/RECORD
