Metadata-Version: 2.1
Name: reckomate-ai-sdk
Version: 0.2.0
Summary: Reckomate internal Python SDK
Author: Harish Kumar
Author-email: your_email@gmail.com
Classifier: Programming Language :: Python :: 3
Classifier: License :: OSI Approved :: MIT License
Classifier: Operating System :: OS Independent
Requires-Python: >=3.9
Requires-Dist: fastapi
Requires-Dist: pydantic
Requires-Dist: python-dotenv
Requires-Dist: pymongo
Requires-Dist: qdrant-client
Requires-Dist: requests
